cms_test_app/__init__.py
cms_test_app/admin.py
cms_test_app/apps.py
cms_test_app/models.py
cms_test_app/tests.py
cms_test_app/urls.py
cms_test_app/views.py
cms_test_app/management/__init__.py
cms_test_app/management/commands/__init__.py
cms_test_app/management/commands/fix_permissions.py
cms_test_app/migrations/__init__.py
cms_test_app/static/__init__.py
cms_test_app-1.1.0.dist-info/LICENSE.txt
cms_test_app-1.1.0.dist-info/METADATA
cms_test_app-1.1.0.dist-info/WHEEL
cms_test_app-1.1.0.dist-info/top_level.txt
cms_test_app-1.1.0.dist-info/RECORD
