Metadata-Version: 2.1
Name: cms-test-app
Version: 1.1.0
Summary: CMS project
Home-page: https://github.com/DianaHov/test-cms
Author: Diana Hovhannisyan
Author-email: d.hovhannisyan@gmail.com
License: UNKNOWN
Keywords: cms django workflow
Platform: UNKNOWN
Classifier: Development Status :: 3 - Alpha
Classifier: Intended Audience :: Developers
Classifier: Topic :: Software Development :: Build Tools
Classifier: License :: OSI Approved :: MIT License
Classifier: Programming Language :: Python :: 2.7
Requires-Python: >=2.7, !=3.0.*, !=3.1.*, !=3.2.*, !=3.3.*, <4
Requires-Dist: cms-test-app
Requires-Dist: Django
